py_mail
