Metadata-Version: 2.1
Name: py-mail
Version: 0.0.4
Summary: Provides data from the gmail mailbox in a human readable type
Home-page: https://github.com/VladimirPodolyan/py-mail
Author: PVladimir
Author-email: vladimir.podolyan64@gmail.com
License: UNKNOWN
Platform: UNKNOWN
Classifier: Programming Language :: Python :: 3.7
